{
  "version": "0.1.0",
  "author": "Jakub Andrysek",
  "github": "JakubAndrysek",
  "license": "MIT",

  "category": "smartled_ext",
  "parentCategory": "smartled",
  "name": "%T%",
  "description": "%T%",
  "docs": "/docs/blocks/smartled-ext",
  "colour": "#A58F5C",
  "icon": "Lightbulb",
  "priority": 135,
  "libraries": [
    "import { SmartLedExt } from \"smartled-ext\";",
    "import { LED_WS2812, LED_WS2812B, LED_WS2812B_2020, LED_SK6812, LED_WS2813 } from \"smartled\";",
    "import * as colors from \"colors\";"
  ],
  "contents": [
    {
      "kind": "block",
      "type": "strip_ext_constructor",
      "message0": "%T%",
      "args0": [
        {
          "type": "field_input",
          "name": "CONSTRUCTED_VAR_NAME",
          "text": "strip_?"
        },
        {
          "type": "input_value",
          "name": "LED_PIN",
          "check": "Number",
          "shadow": {
            "type": "math_number",
            "fields": { "NUM": 42 }
          }
        },
        {
          "type": "input_value",
          "name": "LED_COUNT",
          "check": "Number",
          "shadow": {
            "type": "math_number",
            "fields": { "NUM": 8 }
          }
        },
        {
          "type": "field_dropdown",
          "name": "LED_TYPE",
          "options": [
            ["%LED_WS2812%", "LED_WS2812"],
            ["%LED_WS2812B%", "LED_WS2812B"],
            ["%LED_WS2812B_2020%", "LED_WS2812B_2020"],
            ["%LED_SK6812%", "LED_SK6812"],
            ["%LED_WS2813%", "LED_WS2813"]
          ]
        }
      ],
      "constructs": "strip",
      "tooltip": "%T%",
      "code": "const $[CONSTRUCTED_VAR_NAME] = new SmartLedExt($[LED_PIN], $[LED_COUNT], $[LED_TYPE]);",
      "previousStatement": null,
      "nextStatement": null
    },
    {
      "kind": "block",
      "type": "strip_ext_set_all",
      "message0": "%T%",
      "args0": [
        {
          "type": "field_dropdown",
          "name": "STRIP_INSTANCE",
          "instanceof": "strip"
        },
        {
          "type": "input_value",
          "name": "COLOR_RGB",
          "check": "ColorRGB",
          "shadow": {
            "type": "dynamic_color_rgb",
            "fields": {
              "MODE": "PALETTE",
              "COLOR_VAL": "#ff0000"
            }
          }
        }
      ],
      "tooltip": "%T%",
      "inputsInline": true,
      "code": "$[STRIP_INSTANCE].setAll($[COLOR_RGB]);",
      "previousStatement": null,
      "nextStatement": null
    },
    {
      "kind": "block",
      "type": "strip_ext_max_brightness",
      "message0": "%T%",
      "args0": [
        {
          "type": "field_dropdown",
          "name": "STRIP_INSTANCE",
          "instanceof": "strip"
        },
        {
          "type": "input_value",
          "name": "BRIGHTNESS",
          "check": "Number",
          "shadow": {
            "type": "math_number",
            "fields": { "NUM": 255 }
          }
        }
      ],
      "tooltip": "%T%",
      "inputsInline": true,
      "code": "$[STRIP_INSTANCE].maxBrightness = $[BRIGHTNESS];",
      "previousStatement": null,
      "nextStatement": null
    },
    {
      "kind": "block",
      "type": "strip_ext_max_brightness_percent",
      "message0": "%T%",
      "args0": [
        {
          "type": "field_dropdown",
          "name": "STRIP_INSTANCE",
          "instanceof": "strip"
        },
        {
          "type": "input_value",
          "name": "PERCENT",
          "check": "Number",
          "shadow": {
            "type": "math_number",
            "fields": { "NUM": 100 }
          }
        }
      ],
      "tooltip": "%T%",
      "inputsInline": true,
      "code": "$[STRIP_INSTANCE].setMaxBrightnessPercent($[PERCENT]);",
      "previousStatement": null,
      "nextStatement": null
    },
    {
      "kind": "block",
      "type": "strip_ext_linearize",
      "message0": "%T%",
      "args0": [
        {
          "type": "field_dropdown",
          "name": "STRIP_INSTANCE",
          "instanceof": "strip"
        },
        {
          "type": "field_dropdown",
          "name": "ENABLED",
          "options": [
            ["%STRIP_EXT_LINEARIZE_ENABLED%", "true"],
            ["%STRIP_EXT_LINEARIZE_DISABLED%", "false"]
          ]
        }
      ],
      "tooltip": "%T%",
      "inputsInline": true,
      "code": "$[STRIP_INSTANCE].doLinearize = $[ENABLED];",
      "previousStatement": null,
      "nextStatement": null
    }
  ]
}
